zigzagcases/__init__.py
zigzagcases/main.py
zigzag_cases-0.6.0.dist-info/METADATA
zigzag_cases-0.6.0.dist-info/WHEEL
zigzag_cases-0.6.0.dist-info/top_level.txt
zigzag_cases-0.6.0.dist-info/RECORD
