Metadata-Version: 2.1
Name: zigzag-cases
Version: 0.6.0
Summary: This is very short description
Author: Avinash R
